jprcfai/__init__.py
jprcfai/apply_changes_from_intructions.py
jprcfai/code_review_utils.py
jprcfai/complex_coding_tasks.py
jprcfai/core.py
jprcfai/logger_config.py
jprcfai/manual_prompt_engineering.py
jprcfai/simple_coding_tasks.py
jprcfai/assistants/CheckpointStatus.txt
jprcfai/assistants/CheckpointerRedirecter.txt
jprcfai/assistants/CodeFixer.txt
jprcfai/assistants/PromptRefactor.txt
jprcfai/assistants/Refactor.txt
jprcfai/assistants/RefactorPython.txt
jprcfai/assistants/RefactorSummary.txt
jprcfai/assistants/RetrieveInfomaton.txt
jprcfai/assistants/ReviewCode.txt
jprcfai/assistants/SelectCandidateFiles.txt
jprcfai/assistants/SingleFileCodeModifications.txt
jprcfai-0.2.18.dist-info/METADATA
jprcfai-0.2.18.dist-info/WHEEL
jprcfai-0.2.18.dist-info/top_level.txt
jprcfai-0.2.18.dist-info/RECORD
