Metadata-Version: 2.4
Name: jprcfai
Version: 0.2.18
Summary: A package that provides advanced coding tools using the new openAI reasoning models.
Home-page: https://github.com/Joaoprcf/jprcfai
Author: Joao Ferreira
Author-email: joaoprcf@gmail.com
Classifier: Programming Language :: Python :: 3
Classifier: Operating System :: OS Independent
Requires-Dist: requests
Requires-Dist: platformdirs
